topsis/101903373.py
topsis/__init__.py
Topsis_Prabhjot_101903373-0.0.1.dist-info/METADATA
Topsis_Prabhjot_101903373-0.0.1.dist-info/WHEEL
Topsis_Prabhjot_101903373-0.0.1.dist-info/top_level.txt
Topsis_Prabhjot_101903373-0.0.1.dist-info/RECORD
